dpgmagictag/__init__.py
dpgmagictag/bases.py
dpgmagictag/context.py
dpgmagictag/magictag.py
dpgmagictag/path.py
dpgmagictag/py.typed
dpgmagictag-0.1.1.dist-info/METADATA
dpgmagictag-0.1.1.dist-info/WHEEL
dpgmagictag-0.1.1.dist-info/licenses/LICENSE.md
dpgmagictag-0.1.1.dist-info/RECORD
