Metadata-Version: 2.4
Name: dpgmagictag
Version: 0.1.1
Summary: A composable tag system for use with DearPyGUI
Author-email: Zachary Parmley <zachary.parmley@gmail.com>
License-Expression: MIT
License-File: LICENSE.md
Classifier: License :: OSI Approved :: MIT License
Classifier: Operating System :: OS Independent
Classifier: Programming Language :: Python :: 3
Classifier: Topic :: Software Development :: User Interfaces
Requires-Python: >=3.10
